Workbook

Sheet 0_README
B2: BÀI LAB 120 PHÚT: AI MONETIZATION & UNIT ECONOMICS MODEL
B3: Học viên: Thân Thị Kim Chi | Mã học viên: 2A202602797 | Lớp: Track 1 - Day 22
B4: Sản phẩm: GitReview AI (Autonomous PR Review & Vulnerability Gatekeeper Agent)
B6: 1. QUY ƯỚC MÀU SẮC Ô TÍNH
B7: Màu sắc | C7: Ý nghĩa | D7: Quy định thao tác
B8: 🟡 Màu Vàng (Yellow) | C8: Ô giả định / Dữ liệu đầu vào | D8: Người dùng phải điền vào các ô này
B9: ⬜ Màu Xám (Gray) | C9: Công thức tự động (Formulas) | D9: TUYỆT ĐỐI KHÔNG sửa, Excel tự động tính toán
B10: 🟩 Màu Xanh (Green) | C10: Đạt chỉ số chuẩn (Pass Benchmark) | D10: Chỉ số an toàn, lành mạnh về mặt tài chính
B11: 🟥 Màu Đỏ (Red) | C11: Cảnh báo nguy hiểm (Alert / Fail) | D11: Cần quay lại điều chỉnh giả định mô hình
B13: 2. QUY ƯỚC DỮ LIỆU & TIỀN TỆ
B14: Ngày chốt giá API | C14: 26/08/2026 | D14: Đã đối soát với trang tài liệu gốc Anthropic & OpenAI
B15: Đơn vị tiền tệ gốc | C15: USD ($) | D15: Giá API & SaaS tiêu chuẩn quốc tế
B16: Tỷ giá quy đổi giả định | C16: 26.000 VNĐ / USD | D16: Dùng cho tham chiếu ngân sách nội địa
B17: Mẫu số Cost/Job | C17: Số Job HOÀN THÀNH (Completed Jobs) | D17: Mẫu số = Khối lượng thử × Containment Rate
B18: Mục tiêu Gross Margin | C18: ≥ 60.0% (AI-native healthy band) | D18: Benchmark ngành AI 2026: 52-53%, Bessemer SaaS: 65%

Sheet 1_Cost_Job
B2: TAB 1: TÍNH TOÁN CHI PHÍ COST / JOB ĐỦ 5 THÀNH PHẦN
B4: Khoản mục / Tham số | C4: Giá trị / Giả định | D4: Đơn vị tính | E4: Ghi chú & Căn cứ số liệu
B5: S1. ĐỊNH NGHĨA JOB (JOB-TO-BE-DONE)
B6: Tên Job chuẩn hóa | C6: 1 PR Reviewed & Actionable | D6: PR completed | E6: Đếm tự động qua GitHub webhook
B7: Định nghĩa chi tiết 1 Job | C7: 1 Pull Request được rà soát code diff, phát hiện lỗi logic/bảo mật, tự động Approve hoặc comment chính xác dòng code cần sửa. | D7: Văn bản định nghĩa | E7: Định nghĩa chặt chẽ: chỉ tính tiền khi PR Merged hoặc dev chấp nhận inline fix
B8: S2. KHỐI LƯỢNG & TỶ LỆ HOÀN THÀNH (VOLUME & CONTAINMENT)
B9: Tổng số job thử nghiệm / tháng (Attempted Jobs) | C9: 1000 | D9: PRs / tháng | E9: Quy mô team công nghệ 25-40 devs
B10: Containment Rate (Tỷ lệ AI tự xử lý xong %) | C10: 0.85 | D10: % tự động | E10: Đo từ Eval tập 500 PRs thực tế (85% không cần người hỗ trợ)
B11: Số job HOÀN THÀNH / tháng (Completed Jobs) [MẪU SỐ] | C11: =C9*C10 | D11: PRs hoàn thành | E11: ⚠️ MẪU SỐ THẬT: Tuyệt đối không chia cho 1.000 job thử
B12: S3. CHI PHÍ MÔ HÌNH NGÔN NGỮ (LLM TOKENS VỚI PROMPT CACHING)
B13: Model sử dụng chính | C13: Claude Haiku 4.5 | D13: Anthropic | E13: Giá niêm yết: $1.00/1M input, $5.00/1M output, Cache: $0.10/1M
B14: Input Token Cacheable (System prompt + KB + Styleguide) | C14: 9000 | D14: tokens / PR | E14: Repository context & coding guidelines (lặp lại liên tục)
B15: Input Token Fresh (Git diff mới của PR) | C15: 3500 | D15: tokens / PR | E15: Mã nguồn thay đổi thực tế của pull request
B16: Output Token (Review summary + inline comments) | C16: 800 | D16: tokens / PR | E16: Nhận xét súc tích, chỉ trỏ đúng dòng code sai
B17: Đơn giá Cache Read / 1M token | C17: 0.1 | D17: $ / 1M tokens | E17: Anthropic Cache Read = 0.1x giá input thường
B18: Đơn giá Input thường / 1M token | C18: 1 | D18: $ / 1M tokens | E18: Anthropic Claude Haiku 4.5 Fresh Input
B19: Đơn giá Output / 1M token | C19: 5 | D19: $ / 1M tokens | E19: Anthropic Claude Haiku 4.5 Output
B20: Chi phí LLM cho 1 PR (CÓ Prompt Caching) | C20: =(C14*C17/1000000)+(C15*C18/1000000)+(C16*C19/1000000) | D20: $ / PR | E20: Tiết kiệm 47.5% so với không cache ($0.0160)
B21: Tổng chi phí LLM cho 1.000 PR thử / tháng | C21: =C9*C20 | D21: $ / tháng | E21: Tổng hóa đơn Anthropic trực tiếp
B22: S4. SPEECH (THOẠI - NẾU CÓ)
B23: Chi phí Voice / Audio STT & TTS | C23: 0 | D23: $ / tháng | E23: Sản phẩm thuần Git Text Diff, không dùng Speech
B24: S5. HẠ TẦNG & LƯU TRỮ (INFRASTRUCTURE & LOGGING)
B25: Đơn giá Infra trên mỗi PR thử | C25: 0.02 | D25: $ / PR | E25: Vector DB (Qdrant Cloud), Webhook runner (AWS Lambda), Egress
B26: Tổng chi phí Infra cho 1.000 PR / tháng | C26: =C9*C25 | D26: $ / tháng | E26: Chi phí máy chủ & vector search hàng tháng
B27: S6. TỶ LỆ GỌI LẠI (RETRY RATE) ⚠️ KHÔNG ĐỂ 0%
B28: Tỷ lệ retry do timeout, network lag, JSON format error | C28: 0.08 | D28: % retry | E28: 8% tỷ lệ gọi lại thực tế (chuẩn công nghiệp 5-10%)
B29: Chi phí Retry cộng thêm hàng tháng | C29: =C21*C28 | D29: $ / tháng | E29: 8% token LLM tốn thêm do phải retry
B30: S7. HUMAN-IN-THE-LOOP (HITL) & NỘI BỘ QA
B31: Biến thể HITL áp dụng | C31: Biến thể A (SaaS) | D31: Mô hình | E31: Khách tự xử lý ca escalate; Nhà cung cấp chịu chi phí QA định kỳ
B32: Tỷ lệ PR lấy mẫu kiểm định QA định kỳ | C32: 0.05 | D32: % lấy mẫu | E32: 5% số PR được Senior AI Engineer kiểm tra chéo
B33: Thời gian kiểm tra trung bình mỗi ca | C33: 0.05 | D33: giờ / ca | E33: 3 phút = 0.05 giờ
B34: Chi phí nhân sự QA nội bộ / giờ | C34: 10 | D34: $ / giờ | E34: Chi phí nhân lực QA chuyên trách
B35: Tổng chi phí HITL QA nội bộ hàng tháng | C35: =C9*C32*C33*C34 | D35: $ / tháng | E35: 1.000 PR * 5% * 0.05h * $10 = $25.00/tháng
B36: S8. OVERHEAD PHÂN BỔ (OBSERVABILITY & EVALS)
B37: Chi phí LangSmith/Helicone tracing & evals tooling | C37: 6 | D37: $ / tháng | E37: Hệ thống giám sát trôi dạt dữ liệu và prompt versioning
B38: TỔNG HỢP CHI PHÍ & TÍNH TOÁN COST / JOB
B39: TỔNG CHI PHÍ VẬN HÀNH / THÁNG (COGS) | C39: =C21+C23+C26+C29+C35+C37 | D39: $ / tháng | E39: Tổng COGS = LLM + Speech + Infra + Retry + HITL + Overhead
B40: COST / JOB (CHI PHÍ TRÊN MỖI JOB HOÀN THÀNH) | C40: =C39/C11 | D40: $ / job completed | E40: ⭐ CON SỐ SỐNG CÒN: Chia cho C11 (850 job), không chia 1.000
B41: Quy đổi tiền Việt (Tỷ giá 26.000 ₫/USD) | C41: =C40*26000 | D41: VNĐ / PR | E41: Chỉ khoảng ~1.846 VNĐ cho 1 PR hoàn chỉnh

Sheet 2_Pricing
B2: TAB 2: VÙNG GIÁ BÁN, GROSS MARGIN & BREAKEVEN ANALYSIS
B4: Tham số định giá | C4: Giá trị tính toán | D4: Đơn vị tính | E4: Căn cứ & Nhận xét
B5: 1. XÁC ĐỊNH GIÁ SÀN & GIÁ BÁN ĐỀ XUẤT
B6: Cost / Job (Lấy từ Tab 1) | C6: ='1_Cost_Job'!C40 | D6: $ / job | E6: Lấy trực tiếp từ Tab 1_Cost_Job
B7: Giá sàn tối thiểu (= 3 × Cost/Job) | C7: =C6*3 | D7: $ / job | E7: Ngưỡng sàn đảm bảo cover R&D, sales và biến động token
B8: GIÁ BÁN ĐỀ XUẤT (PROPOSED PRICE / JOB) | C8: 0.6 | D8: $ / job | E8: Đơn giá $0.60 / PR (Gói Pro $59/tháng kèm 100 PRs)
B9: GROSS MARGIN TRÊN ĐƠN VỊ PR (GM %) | C9: =(C8-C6)/C8 | D9: % lợi nhuận gộp | E9: 🟩 ĐẠT NGƯỠNG (Mục tiêu ≥ 60.0%)
B10: 2. NEO GIÁ TRẦN (PRICE ANCHORING)
B11: Chi phí nhân công thủ công (Lương Tech Lead review PR) | C11: 12.5 | D11: $ / PR | E11: Lương Tech Lead $2.500/tháng cho ~200 PRs (tương đương $12.5/PR)
B12: Mức tiết kiệm cho khách hàng trên mỗi PR | C12: =C11-C8 | D12: $ tiết kiệm | E12: Tiết kiệm $11.90/PR (Khách tiết kiệm >95% chi phí thời gian)
B13: Tỷ lệ giá bán so với chi phí nhân công bị thay thế | C13: =C8/C11 | D13: % lương nhân sự | E13: Chỉ chiếm 4.8% chi phí tuyển dụng nhân sự (Cực kỳ hấp dẫn)
B14: 3. ĐIỂM HÒA VỐN SỐNG CÒN (BREAKEVEN CONTAINMENT RATE)
B15: Cost/Job tối đa cho phép để giữ GM ≥ 60% | C15: =C8*(1-0.60) | D15: $ / job | E15: Ở giá $0.60, Cost/Job không được vượt quá $0.24
B16: Số job hoàn thành tối thiểu cần đạt (trên 1.000 job) | C16: ='1_Cost_Job'!C39/C15 | D16: jobs completed | E16: Công thức: Tổng chi phí $60.07 / $0.24 = 251 jobs
B17: BREAKEVEN CONTAINMENT RATE (NGƯỠNG SỐNG CÒN) | C17: =C16/'1_Cost_Job'!C9 | D17: % tối thiểu | E17: 🟩 Chỉ cần đạt ≥ 25.1% là có lãi lành mạnh (Eval đạt 85%)
B19: 4. BẢNG PHÂN TÍCH ĐỘ NHẠY (SENSITIVITY ANALYSIS)
B20: Containment Rate % | C20: Job hoàn thành | D20: Cost / Job ($) | E20: Gross Margin (%)
B21: 0.5 | C21: ='1_Cost_Job'!$C$9*B21 | D21: ='1_Cost_Job'!$C$39/C21 | E21: =($C$8-D21)/$C$8
B22: 0.6 | C22: ='1_Cost_Job'!$C$9*B22 | D22: ='1_Cost_Job'!$C$39/C22 | E22: =($C$8-D22)/$C$8
B23: 0.7 | C23: ='1_Cost_Job'!$C$9*B23 | D23: ='1_Cost_Job'!$C$39/C23 | E23: =($C$8-D23)/$C$8
B24: 0.8 | C24: ='1_Cost_Job'!$C$9*B24 | D24: ='1_Cost_Job'!$C$39/C24 | E24: =($C$8-D24)/$C$8
B25: 0.85 | C25: ='1_Cost_Job'!$C$9*B25 | D25: ='1_Cost_Job'!$C$39/C25 | E25: =($C$8-D25)/$C$8
B26: 0.9 | C26: ='1_Cost_Job'!$C$9*B26 | D26: ='1_Cost_Job'!$C$39/C26 | E26: =($C$8-D26)/$C$8

Sheet 3_Value_Metric
B2: TAB 3: VALUE METRIC & MA TRẬN ATTRIBUTION × AUTONOMY
B4: Tiêu chí đánh giá | C4: Điểm số / Đánh giá | D4: Thang điểm | E4: Bằng chứng & Lập luận
B5: 1. ĐÁNH GIÁ MA TRẬN ATTRIBUTION × AUTONOMY
B6: Độ tự động hóa (Autonomy Score) | C6: 8.5 | D6: Điểm / 10 | E6: AI tự quét code diff, tự comment dòng code sai, dev chỉ bấm 1 nút áp dụng
B7: Khả năng đo lường kết quả (Attribution Score) | C7: 9 | D7: Điểm / 10 | E7: Đo được 100% qua GitHub Webhook: số lỗi bắt được, commit sửa theo AI
B8: Gợi ý từ ma trận lý thuyết | C8: Outcome / Hybrid | D8: Mô hình | E8: Thuộc ô góc phần tư CAO × CAO (Lý tưởng cho Outcome/Hybrid)
B9: 2. CHỐT VALUE METRIC LỰA CHỌN
B10: Value Metric chính thức | C10: HYBRID PRICING | D10: Đơn vị tính tiền | E10: Phí nền Repository/tháng + Gói PR Usage bổ sung
B11: Cấu trúc gói giá đề xuất | C11: $49/repo/tháng + $1.50/PR vượt quota (tặng sẵn 50 PR/tháng) | D11: Chi tiết gói | E11: Bảo vệ margin khi khách dùng ít, không giới hạn seat người dùng
B12: 3. DECISION NOTE (3 CÂU BẢO VỆ ĐƠN VỊ TÍNH TIỀN)
B13: Câu 1: Tôi chọn đơn vị nào? | C13: Tôi chọn Hybrid Pricing: Phí nền $49/repo/tháng + $1.50/PR vượt ngưỡng thay vì Seat thuần để loại bỏ rủi ro marginal cost khi dev spam code.
B14: Câu 2: Attribution & Autonomy mức nào? | C14: Sản phẩm đạt Autonomy 8.5/10 và Attribution 9.0/10 nhờ cắm trực tiếp vào GitHub Webhook, ghi nhận chính xác 100% từng PR được giải quyết.
B15: Câu 3: Lý do thị trường (Market Override)? | C15: Tại thị trường B2B công nghệ, CTO và phòng Tài chính cần một hóa đơn có thể dự báo được (predictable spend) thay vì biến thiên 100% rủi ro.
B16: 4. BENCHMARK ĐỐI THỦ THẬT CÓ NGUỒN (BENCHMARK AUDIT)
B17: Tên sản phẩm đối thủ | C17: Mô hình tính tiền | D17: Mức giá công bố | E17: Link nguồn kiểm tra
B18: CodeRabbit | C18: Hybrid (Gói team + hạn mức credit review repo) | D18: $15 - $24 / dev / tháng | E18: https://coderabbit.ai/pricing
B19: GitHub Copilot | C19: Hybrid (Phí nền seat + AI Credits cho agent tác vụ) | D19: $19 / seat + $0.01 / AI Credit bổ sung | E19: https://github.com/features/copilot/plans
B20: Intercom Fin | C20: Outcome thuần (Resolution-based) | D20: $0.99 / resolution | E20: https://fin.ai/pricing/

Sheet 4_Channel_Fit
B2: TAB 4: KÊNH PHÂN PHỐI & CHANNEL AFFORDABILITY TEST
B4: Chỉ số tài chính | C4: Giá trị tính toán | D4: Đơn vị tính | E4: Căn cứ & Nhận xét
B5: 1. TÍNH TOÁN NGÂN SÁCH CAC TỐI ĐA CHO PHÉP
B6: Doanh thu trung bình trên khách (ARPU / tháng) | C6: 149 | D6: $ / tháng | E6: Gói Pro $149/tháng (phục vụ 10 repos, ~200 PRs/tháng)
B7: Gross Margin tổng thể (GM %) | C7: 0.685 | D7: % biên gộp | E7: Biên lợi nhuận gộp toàn dịch vụ (bao gồm hạ tầng base)
B8: Số tháng thu hồi vốn CAC cho phép (Payback Period) | C8: 12 | D8: tháng | E8: Chuẩn Bessemer 2024 cho phân khúc SMB (<12 tháng)
B9: NGÂN SÁCH CAC TỐI ĐA / KHÁCH HÀNG | C9: =C6*C7*C8 | D9: $ / khách | E9: Công thức: ARPU * GM * Số tháng payback = $1,224.78
B10: 2. KIỂM ĐỊNH TÍNH KHẢ THI CỦA INSIDE SALES (TUNGUZ TEST)
B11: Giá trị hợp đồng năm (ACV = ARPU × 12) | C11: =C6*12 | D11: $ / năm | E11: $149 * 12 = $1,788/năm
B12: Chỉ tiêu doanh số 1 nhân viên Sales (Quota / năm) | C12: 360000 | D12: $ / năm | E12: Chuẩn Inside Sales B2B tech ($300k - $500k/năm)
B13: Số deal 1 Sales phải chốt trong năm | C13: =C12/C11 | D13: deals / năm | E13: Phải chốt 201 deal/năm mới đạt quota
B14: Số deal 1 Sales phải chốt MỖI NGÀY LÀM VIỆC | C14: =C13/250 | D14: deals / ngày | E14: 🟥 0.80 deal/ngày (Áp lực phi thực tế với B2B Bán hàng)
B15: Chi phí thực tế 1 cơ hội bán hàng (Cost per Opportunity) | C15: 6300 | D15: $ / opp | E15: Benchmark ICONIQ 2026 cho phân khúc SMB B2B
B16: Tỷ lệ chốt thành công (Win Rate %) | C16: 0.2 | D16: % win | E16: Tỷ lệ chuẩn 20% chốt từ demo
B17: CAC thực tế ước tính nếu dùng Sales Reps | C17: =C15/C16 | D17: $ / khách | E17: 🟥 CAC thực tế lên tới $31,500/khách!
B18: ĐỘ LỆCH GIỮA CAC THỰC TẾ VÀ NGÂN SÁCH CHO PHÉP | C18: =C17/C9 | D18: lần vượt trần | E18: 🟥 Lệch 25.7 lần ➔ Tuyệt đối KHÔNG chạy Sales-Led!
B19: 3. CHỐT KÊNH GTM DUY NHẤT CHO 90 NGÀY ĐẦU
B20: KÊNH PHÂN PHỐI ĐÃ CHỐT | C20: PLG + GITHUB MARKETPLACE | D20: Kênh duy nhất | E20: Product-Led Growth cắm trực tiếp vào GitHub App
B21: CAC thực tế của kênh PLG | C21: 180 | D21: $ / khách | E21: Chi phí content marketing, docs và listing GitHub
B22: Thời gian thu hồi vốn thực tế (Actual Payback) | C22: =C21/(C6*C7) | D22: tháng | E22: 🟩 Chỉ mất 1.8 tháng để thu hồi CAC (Cực kỳ xuất sắc)

Sheet 5_90Day_Plan
B2: TAB 5: KẾ HOẠCH 90 NGÀY & CHECKLIST EVIDENCE PACK
B4: 1. PAIN MOMENT ĐỦ 3 YẾU TỐ CHUẨN MỰC
B5: MẤY GIỜ? | C5: 23h15 đêm | D5: Thời điểm dev vừa push code xong trước release
B6: ĐANG LÀM GÌ? | C6: Tạo Pull Request và chờ Tech Lead review | D6: Tech Lead đã offline, PR bị nghẽn tắc, pipeline CI/CD treo
B7: DÙNG APP NÀO? | C7: Giao diện GitHub Pull Request | D7: Dev đang ngồi tại tab PR của GitHub web
B8: ĐIỂM NHÚNG (SURFACE) | C8: GitHub App Webhook cắm trực tiếp vào repo | D8: Zero friction: nhận xét inline ngay tại tab Files Changed
B10: 2. KẾ HOẠCH PHÂN PHỐI 90 NGÀY (3 GIAI ĐOẠN)
B11: Giai đoạn | C11: Mục tiêu trọng tâm | D11: Chỉ số KPI có số | E11: Người chịu trách nhiệm
B12: Tháng 1: Học sâu (Learning) | C12: Onboard 15 team công nghệ thân thiết (Design Partners), theo dõi trực tiếp từng comment của bot, tối ưu prompt | D12: 15 active repos, độ chính xác review > 90% | E12: Founder & AI Engineer
B13: Tháng 2-3: Đòn bẩy (Leverage) | C13: Publish chính thức lên GitHub Marketplace, chạy technical blog trên HackerNews/Dev.to, kích hoạt freemium tier | D13: 150 installs, 35 khách hàng trả phí Pro ($149) | E13: Product Lead & Tech Marketer
B14: Tháng 4+: Mở rộng (Expand) | C14: Hỗ trợ thêm GitLab & Bitbucket Server cho các khách hàng doanh nghiệp tài chính / bảo mật cao | D14: $15,000 MRR, tỷ lệ churn < 3%/tháng | E14: Full Engineering Team
B16: 3. CHECKLIST EVIDENCE PACK CHO PROCUREMENT & IT
B17: Tài sản bán hàng | C17: Trạng thái / Nội dung cụ thể | D17: Bằng chứng văn bản | E17: Người phụ trách / Deadline
B18: Eval Results | C18: Đạt độ chính xác 92.4% trên bộ 500 PRs thực tế, false positive 4.8%, thời gian phản hồi 38s | D18: Báo cáo Eval Benchmark PDF kèm metrics | E18: AI Engineer (Đã có sẵn)
B19: Procurement Q&A | C19: Cam kết ZDR (Zero Data Retention), không train model trên code khách, xóa bộ nhớ ephemeral sau khi post comment | D19: Bản cam kết bảo mật & pháp lý 5 trang | E19: Founder & Legal (30/10/2026)
B20: Pilot Report | C20: Thử nghiệm 4 tuần tại công ty 30 devs: Giảm PR review turnaround time từ 18.4 giờ xuống 42 phút, tiết kiệm 28h/tháng cho Tech Lead | D20: Pilot Case Study có xác nhận của CTO khách | E20: Product Lead (Đã hoàn thành)

Sheet 6_Benchmarks
B2: TAB 6: BẢNG GIÁ THAM CHIẾU API & SẢN PHẨM NGÀNH (CHỐT 26/08/2026)
B4: Nhà cung cấp / Dịch vụ | C4: Model / Gói cước | D4: Đơn giá niêm yết (USD) | E4: Ghi chú & Trạng thái khuyến mại
B5: Anthropic | C5: Claude Haiku 4.5 | D5: $1.00 input / $5.00 output / $0.10 cache read per 1M | E5: Giá chính thức, cache hit giảm 90% input
B6: Anthropic | C6: Claude Sonnet 3.5 | D6: $3.00 input / $15.00 output / $0.30 cache read per 1M | E6: Dùng cho các ca phân tích kiến trúc phức tạp
B7: OpenAI | C7: GPT-4o-mini | D7: $0.15 input / $0.60 output / $0.075 cache read per 1M | E7: Model siêu rẻ cho tác vụ linting
B8: Google Cloud | C8: Gemini 3.7 Flash | D8: $0.75 input / $3.75 output per 1M | E8: ⏳ Giá khuyến mại đến 31/12/2026
B9: Deepgram | C9: Nova-3 STT | D9: $0.0043 / phút (pre-recorded) | E9: Dịch vụ bóc băng âm thanh
B10: ElevenLabs | C10: Flash / Turbo TTS | D10: $50 / 1M ký tự | E10: Dịch vụ đọc văn bản thành giọng nói
B11: Intercom | C11: Fin AI Agent | D11: $0.99 / resolution | E11: Benchmark tính tiền theo Outcome chuẩn mực
B12: GitHub | C12: Copilot Business | D12: $19 / seat / tháng + AI Credits | E12: Benchmark chuyển đổi từ seat sang usage
